microprocessors/__init__.py
microprocessors/architechture.py
microprocessors/processors.py
microprocessors/tests.py
microprocessors-0.1.8.dist-info/LICENSE
microprocessors-0.1.8.dist-info/METADATA
microprocessors-0.1.8.dist-info/WHEEL
microprocessors-0.1.8.dist-info/top_level.txt
microprocessors-0.1.8.dist-info/RECORD
